{"inkVersion":20,"root":[["ev",0,{"x()":"ChangeTime","exArgs":1},"out","/ev","\n","^Memang benar siswa akan semakin giat belajar dengan adanya Ujian Nasional. Akan tetapi, hal tersebut akan membimbing siswa kepada suatu konsep belajar yang keliru.","\n","ev","str","^Fatih","/str",{"x()":"Name","exArgs":1},"out","/ev","\n","ev","str","^fatih","/str",{"x()":"Icon","exArgs":1},"out","/ev","\n","ev","str","^chitose","/str","str","^AgreeWithYou","/str",{"x()":"CharAnimation","exArgs":2},"out","/ev","\n","ev","str","^chitose","/str",0,{"x()":"CharExpression","exArgs":2},"out","/ev","\n","ev",4,{"x()":"ChangeTime","exArgs":1},"out","/ev","\n","ev",3,{"x()":"TransNum","exArgs":1},"out","/ev","\n","^Memang benar siswa akan semakin giat belajar dengan adanya Ujian Nasional.","\n","ev",5,{"x()":"ChangeTime","exArgs":1},"out","/ev","\n","^Akan tetapi, hal tersebut akan membimbing siswa kepada suatu konsep belajar yang keliru.","\n","ev","str","^chitose","/str","str","^GivinganArgument","/str",{"x()":"CharAnimation","exArgs":2},"out","/ev","\n","ev","str","^chitose","/str",6,{"x()":"CharExpression","exArgs":2},"out","/ev","\n","ev",4,{"x()":"ChangeTime","exArgs":1},"out","/ev","\n","^Siswa hanya akan fokus kepada hasilnya, yaitu berupa nilai yang tinggi, bukan kepada proses belajarnya.","\n","ev",5,{"x()":"ChangeTime","exArgs":1},"out","/ev","\n","ev",true,{"x()":"ShowArgue","exArgs":1},"out","/ev","\n","^Siswa akan beranggapan bahwa tujuan utama belajar di sekolah adalah untuk mendapatkan nilai yang tinggi,","\n","ev",4,{"x()":"ChangeTime","exArgs":1},"out","/ev","\n","^Bukan untuk mendapatkan ilmu yang bermanfaat bagi kehidupan sehari-hari.","\n","ev",3,{"x()":"ChangeTime","exArgs":1},"out","/ev","\n","ev",false,{"x()":"ShowArgue","exArgs":1},"out","/ev","\n","^Hal ini yang akan menuntun siswa kepada kecurangan.","\n","ev","str","^chitose","/str","str","^AgreeWithYou","/str",{"x()":"CharAnimation","exArgs":2},"out","/ev","\n","ev","str","^chitose","/str",0,{"x()":"CharExpression","exArgs":2},"out","/ev","\n","ev",4,{"x()":"ChangeTime","exArgs":1},"out","/ev","\n","^Dapat saya simpulkan bahwa Ujian Nasional tidak dapat dijadikan acuan kelulusan yang efektif,","\n","ev",4,{"x()":"ChangeTime","exArgs":1},"out","/ev","\n","^Karena dapat membimbing siswa kepada tujuan belajar yang salah serta menambah tingkat kecurangan yang terjadi.","\n","ev","str","^2_Intro","/str",{"x()":"ChangeScript","exArgs":1},"out","/ev","\n",["done",{"#f":5,"#n":"g-0"}],null],"done",{"#f":1}],"listDefs":{}}